README.rst
setup.py
verace.py
verace.egg-info/PKG-INFO
verace.egg-info/SOURCES.txt
verace.egg-info/dependency_links.txt
verace.egg-info/requires.txt
verace.egg-info/top_level.txt