Metadata-Version: 1.1
Name: verace
Version: 0.3.2
Summary: Library for checking version strings in project files.
Home-page: https://github.com/jeffrimko/Verace
Author: Jeff Rimko
Author-email: jeffrimko@gmail.com
License: MIT
Keywords: project files version check library
Platform: UNKNOWN
Classifier: Development Status :: 4 - Beta
Classifier: Topic :: Utilities
Classifier: Programming Language :: Python :: 2.7
